odoo8_addon_opl_all-8.0.1.0.0-py2.7-nspkg.pth
odoo_addons/opl_all/__openerp__.py
odoo_addons/opl_all/__init__.py
odoo_addons/opl_all/README.rst
odoo_addons/opl_all/i18n/es.po
odoo8_addon_opl_all-8.0.1.0.0.dist-info/top_level.txt
odoo8_addon_opl_all-8.0.1.0.0.dist-info/WHEEL
odoo8_addon_opl_all-8.0.1.0.0.dist-info/RECORD
odoo8_addon_opl_all-8.0.1.0.0.dist-info/metadata.json
odoo8_addon_opl_all-8.0.1.0.0.dist-info/DESCRIPTION.rst
odoo8_addon_opl_all-8.0.1.0.0.dist-info/METADATA
odoo8_addon_opl_all-8.0.1.0.0.dist-info/namespace_packages.txt
